[
  {
    "text": "Math",
    "link": "/math/core course/2 Chapter1 real numbers ratios absolute value Module1 integers fractions decimals part1",
    "activeMatch": "math"
  },
  {
    "text": "Logic",
    "link": "/logic/1 Concepts",
    "activeMatch": "logic"
  },
  {
    "text": "Writing",
    "link": "/writing/1 Concepts",
    "activeMatch": "writing"
  },
  {
    "text": "English",
    "link": "/english/1 Concepts",
    "activeMatch": "english"
  },
  {
    "text": "Resources",
    "link": "/resources/1 Todo",
    "activeMatch": "resources"
  },
  {
    "text": "Concurrent",
    "link": "/java/concurrent/1 线程本质与线程模型",
    "activeMatch": "java/concurrent"
  },
  {
    "text": "Spring",
    "link": "/java/spring/1 xml解析",
    "activeMatch": "java/spring"
  }
]

